MedShapeNetCore/MedShapeNetCore.py
MedShapeNetCore/__init__.py
MedShapeNetCore/__main__.py
MedShapeNetCore/setup.py
MedShapeNetCore-0.1.12.dist-info/METADATA
MedShapeNetCore-0.1.12.dist-info/WHEEL
MedShapeNetCore-0.1.12.dist-info/top_level.txt
MedShapeNetCore-0.1.12.dist-info/zip-safe
MedShapeNetCore-0.1.12.dist-info/RECORD
